{
    "/js/manifest.js": "/js/manifest.js?id=d91051ea7d0c9bd1981e",
    "/js/manifest.js.map": "/js/manifest.js.map?id=a07956f82042cc418451",
    "/js/vendor.js": "/js/vendor.js?id=b3b13ab0d36bc43541ec",
    "/js/vendor.js.map": "/js/vendor.js.map?id=003da11d6432afd14ed6",
    "/js/backend.js": "/js/backend.js?id=f4128f8b92f8642215bf",
    "/js/backend.js.map": "/js/backend.js.map?id=be36bb5fe544fe67c7b4",
    "/js/frontend.js": "/js/frontend.js?id=f3742aef9696264fb977",
    "/css/frontend.css": "/css/frontend.css?id=a38ceb59f30b8194b1fd",
    "/css/backend.css": "/css/backend.css?id=619ed2c05f019e45eb39",
    "/js/frontend.js.map": "/js/frontend.js.map?id=7f1b766199bbb0cfb851"
}
